pycalc_ffg/__init__.py
pycalc_ffg/basic.py
pycalc_ffg/prime.py
pycalc_ffg-0.0.1.dist-info/METADATA
pycalc_ffg-0.0.1.dist-info/WHEEL
pycalc_ffg-0.0.1.dist-info/top_level.txt
pycalc_ffg-0.0.1.dist-info/RECORD
