Metadata-Version: 2.1
Name: pycalc-ffg
Version: 0.0.1
Summary: Simples calculations for python
Home-page: UNKNOWN
Author: Felipe
Author-email: felipe.fgon@gmail.com
License: UNKNOWN
Platform: UNKNOWN
Requires-Python: >=3.8
